nonebot_plugin_track_anime/__init__.py
nonebot_plugin_track_anime/anime.py
nonebot_plugin_track_anime/config.py
nonebot_plugin_track_anime-0.1.13.dist-info/LICENSE
nonebot_plugin_track_anime-0.1.13.dist-info/METADATA
nonebot_plugin_track_anime-0.1.13.dist-info/WHEEL
nonebot_plugin_track_anime-0.1.13.dist-info/RECORD
