Metadata-Version: 2.3
Name: nonebot-plugin-track-anime
Version: 0.1.13
Summary: a tracking anime tool
License: The MIT License (MIT)
Author: lbsucceed
Author-email: woaikanpika123@gmail.com
Requires-Python: >=3.8,<4.0
Classifier: License :: OSI Approved :: MIT License
Requires-Dist: beautifulsoup4 (>=4.11.2,<5.0.0)
Requires-Dist: nonebot-adapter-onebot (>=2.4.4,<3.0.0)
Requires-Dist: nonebot2 (>=2.2.0)
Requires-Dist: pillow (>=10.0.0,<11.0.0)
Requires-Dist: playwright (>=1.28.1,<2.0.0)
Requires-Dist: requests (>=2.25.1,<3.0.0)
Project-URL: Bug Tracker, https://github.com/lbsucceed/nonebot-plugin-track-anime/issues
Project-URL: Home, https://github.com/lbsucceed/nonebot-plugin-track-anime
